llm_mlx.py
llm_mlx-0.4.dist-info/licenses/LICENSE
llm_mlx-0.4.dist-info/METADATA
llm_mlx-0.4.dist-info/WHEEL
llm_mlx-0.4.dist-info/entry_points.txt
llm_mlx-0.4.dist-info/top_level.txt
llm_mlx-0.4.dist-info/RECORD
