Metadata-Version: 2.4
Name: llm-mlx
Version: 0.4
Summary: Support for MLX models in LLM
Author: Simon Willison
License: Apache-2.0
Project-URL: Homepage, https://github.com/simonw/llm-mlx
Project-URL: Changelog, https://github.com/simonw/llm-mlx/releases
Project-URL: Issues, https://github.com/simonw/llm-mlx/issues
Project-URL: CI, https://github.com/simonw/llm-mlx/actions
Classifier: License :: OSI Approved :: Apache Software License
Requires-Python: >=3.9
License-File: LICENSE
Requires-Dist: llm>=0.24
Requires-Dist: mlx-lm
Provides-Extra: test
Requires-Dist: pytest; extra == "test"
Dynamic: license-file
